[
  {
    "id": "5",
    "name": "Sosial şəbəkələr"
  },
  {
    "id": "6",
    "name": "Təhsil"
  },
  {
    "id": "7",
    "name": "Əyləncə"
  },
  {
    "id": "8",
    "name": "Elektron ticarət"
  },
  {
    "id": "9",
    "name": "Media və reklam"
  },
  {
    "id": "10",
    "name": "Ağıllı şəhərlər"
  },
  {
    "id": "11",
    "name": "Nəqliyyat/Loqistika"
  },
  {
    "id": "12",
    "name": "Məhsuldarlıq və Təhlükəsizlik"
  },
  {
    "id": "13",
    "name": "İnfrastruktur və Təhlükəsizlik"
  },
  {
    "id": "14",
    "name": "Sosial"
  },
  {
    "id": "15",
    "name": "Maliyyə"
  },
  {
    "id": "16",
    "name": "Dizayn/İncəsənət"
  },
  {
    "id": "17",
    "name": "Aqrar"
  },
  {
    "id": "18",
    "name": "Müdafiə sənayesi"
  }
]
